bagit.py
ocrd_fork_bagit-1.8.1.post2.data/data/locale/en/LC_MESSAGES/bagit-python.mo
ocrd_fork_bagit-1.8.1.post2.data/scripts/bagit.py
ocrd_fork_bagit-1.8.1.post2.dist-info/METADATA
ocrd_fork_bagit-1.8.1.post2.dist-info/WHEEL
ocrd_fork_bagit-1.8.1.post2.dist-info/top_level.txt
ocrd_fork_bagit-1.8.1.post2.dist-info/RECORD
